README.md
setup.py
sample_package/__init__.py
sample_package/sample.py
tzak_hello_world.egg-info/PKG-INFO
tzak_hello_world.egg-info/SOURCES.txt
tzak_hello_world.egg-info/dependency_links.txt
tzak_hello_world.egg-info/top_level.txt